bitgrad/__init__.py
bitgrad/cli.py
bitgrad/engine.py
bitgrad/nn.py
bitgrad/viz.py
bitgrad-0.1.2.dist-info/METADATA
bitgrad-0.1.2.dist-info/WHEEL
bitgrad-0.1.2.dist-info/entry_points.txt
bitgrad-0.1.2.dist-info/top_level.txt
bitgrad-0.1.2.dist-info/RECORD
