Metadata-Version: 2.4
Name: bitgrad
Version: 0.1.2
Summary: A small autograd engine + neural network + visualization library
Author: Abhishek
Requires-Python: >=3.8
Requires-Dist: graphviz
